mygo/__init__.py
mygo/type.py
mygo/devtools/__init__.py
mygo/id/__init__.py
mygo/id/toid.py
mygo/version/__init__.py
mygo-1.0.1.dist-info/LICENSE
mygo-1.0.1.dist-info/METADATA
mygo-1.0.1.dist-info/WHEEL
mygo-1.0.1.dist-info/top_level.txt
mygo-1.0.1.dist-info/RECORD
