Metadata-Version: 2.1
Name: mygo
Version: 1.0.1
Summary: Some useful tools
Home-page: https://github.com/PythonNotebook/pyMygo
Author: HisAtri
Author-email: yz@ghacg.com
Classifier: Programming Language :: Python :: 3
Classifier: License :: OSI Approved :: MIT License
Classifier: Operating System :: OS Independent
License-File: LICENSE
